anki_vector/__init__.py
anki_vector/animation.py
anki_vector/annotate.py
anki_vector/audio.py
anki_vector/behavior.py
anki_vector/camera.py
anki_vector/color.py
anki_vector/connection.py
anki_vector/events.py
anki_vector/exceptions.py
anki_vector/faces.py
anki_vector/lights.py
anki_vector/mdns.py
anki_vector/motors.py
anki_vector/nav_map.py
anki_vector/objects.py
anki_vector/photos.py
anki_vector/proximity.py
anki_vector/robot.py
anki_vector/screen.py
anki_vector/status.py
anki_vector/touch.py
anki_vector/user_intent.py
anki_vector/util.py
anki_vector/version.py
anki_vector/viewer.py
anki_vector/vision.py
anki_vector/world.py
anki_vector/camera_viewer/__init__.py
anki_vector/configure/__main__.py
anki_vector/messaging/__init__.py
anki_vector/messaging/alexa_pb2.py
anki_vector/messaging/alexa_pb2_grpc.py
anki_vector/messaging/behavior_pb2.py
anki_vector/messaging/behavior_pb2_grpc.py
anki_vector/messaging/client.py
anki_vector/messaging/cube_pb2.py
anki_vector/messaging/cube_pb2_grpc.py
anki_vector/messaging/extensions_pb2.py
anki_vector/messaging/extensions_pb2_grpc.py
anki_vector/messaging/external_interface_pb2.py
anki_vector/messaging/external_interface_pb2_grpc.py
anki_vector/messaging/messages_pb2.py
anki_vector/messaging/messages_pb2_grpc.py
anki_vector/messaging/nav_map_pb2.py
anki_vector/messaging/nav_map_pb2_grpc.py
anki_vector/messaging/protocol.py
anki_vector/messaging/response_status_pb2.py
anki_vector/messaging/response_status_pb2_grpc.py
anki_vector/messaging/settings_pb2.py
anki_vector/messaging/settings_pb2_grpc.py
anki_vector/messaging/shared_pb2.py
anki_vector/messaging/shared_pb2_grpc.py
anki_vector/opengl/__init__.py
anki_vector/opengl/opengl.py
anki_vector/opengl/opengl_vector.py
anki_vector/opengl/opengl_viewer.py
anki_vector/opengl/assets/LICENSE.txt
anki_vector/opengl/assets/cube.jpg
anki_vector/opengl/assets/cube.mtl
anki_vector/opengl/assets/cube.obj
anki_vector/opengl/assets/vector.mtl
anki_vector/opengl/assets/vector.obj
danilov0x33_vector-0.8.1.dist-info/LICENSE.txt
danilov0x33_vector-0.8.1.dist-info/METADATA
danilov0x33_vector-0.8.1.dist-info/WHEEL
danilov0x33_vector-0.8.1.dist-info/top_level.txt
danilov0x33_vector-0.8.1.dist-info/zip-safe
danilov0x33_vector-0.8.1.dist-info/RECORD
